heartbeat_notify/__init__.py
heartbeat_notify/main.py
heartbeat_notify/monitor.py
heartbeat_notify/notifier.py
heartbeat_notify-0.1.2.dist-info/METADATA
heartbeat_notify-0.1.2.dist-info/WHEEL
heartbeat_notify-0.1.2.dist-info/entry_points.txt
heartbeat_notify-0.1.2.dist-info/RECORD
