Metadata-Version: 2.4
Name: heartbeat-notify
Version: 0.1.2
Summary: A tool to monitor file updates and notify via Discord webhook if stalled.
Author-email: User <user@example.com>
Classifier: License :: OSI Approved :: MIT License
Classifier: Operating System :: OS Independent
Classifier: Programming Language :: Python :: 3
Requires-Python: >=3.8
Requires-Dist: click
Requires-Dist: pydantic
Requires-Dist: pyyaml
Requires-Dist: requests
